marshmallow_dataclass2/__init__.py
marshmallow_dataclass2/collection_field.py
marshmallow_dataclass2/generic_resolver.py
marshmallow_dataclass2/lazy_class_attribute.py
marshmallow_dataclass2/mypy.py
marshmallow_dataclass2/py.typed
marshmallow_dataclass2/typing.py
marshmallow_dataclass2/union_field.py
marshmallow_dataclass2-8.8.2.dist-info/LICENSE
marshmallow_dataclass2-8.8.2.dist-info/METADATA
marshmallow_dataclass2-8.8.2.dist-info/WHEEL
marshmallow_dataclass2-8.8.2.dist-info/top_level.txt
marshmallow_dataclass2-8.8.2.dist-info/RECORD
