Metadata-Version: 2.1
Name: marshmallow_dataclass2
Version: 8.8.2
Summary: Python library to convert dataclasses into marshmallow schemas.
Home-page: https://github.com/mvanderlee/marshmallow_dataclass
Author: Ophir LOJKINE, Michiel van der Lee
Author-email: jmt.vanderlee@gmail.com
License: MIT
Keywords: marshmallow,dataclass,serialization
Classifier: Development Status :: 4 - Beta
Classifier: Environment :: Console
Classifier: Operating System :: OS Independent
Classifier: License :: OSI Approved :: MIT License
Classifier: Programming Language :: Python
Classifier: Programming Language :: Python :: 3.9
Classifier: Programming Language :: Python :: 3.10
Classifier: Programming Language :: Python :: 3.11
Classifier: Programming Language :: Python :: 3.12
Classifier: Programming Language :: Python :: 3.13
Classifier: Topic :: Internet :: WWW/HTTP :: Dynamic Content :: CGI Tools/Libraries
Requires-Python: >=3.9
License-File: LICENSE
Requires-Dist: marshmallow >=3.18.0
Requires-Dist: typing-inspect >=0.9.0
Requires-Dist: typeguard <5,>=4.0
Requires-Dist: typing-extensions >=4.2.0 ; python_version < "3.11"
Provides-Extra: dev
Requires-Dist: pre-commit ~=2.17 ; extra == 'dev'
Requires-Dist: sphinx ; extra == 'dev'
Requires-Dist: pytest >=5.4 ; extra == 'dev'
Requires-Dist: pytest-mypy-plugins >=1.2.0 ; (implementation_name != "pypy") and extra == 'dev'
Provides-Extra: docs
Requires-Dist: sphinx ; extra == 'docs'
Provides-Extra: lint
Requires-Dist: pre-commit ~=2.17 ; extra == 'lint'
Provides-Extra: tests
Requires-Dist: pytest >=5.4 ; extra == 'tests'
Requires-Dist: pytest-mypy-plugins >=1.2.0 ; (implementation_name != "pypy") and extra == 'tests'
